AUTHORS
LICENSE
MANIFEST.in
README.rst
setup.py
django_templated_email_django_upgrade.egg-info/PKG-INFO
django_templated_email_django_upgrade.egg-info/SOURCES.txt
django_templated_email_django_upgrade.egg-info/dependency_links.txt
django_templated_email_django_upgrade.egg-info/requires.txt
django_templated_email_django_upgrade.egg-info/top_level.txt
templated_email/__init__.py
templated_email/models.py
templated_email/utils.py
templated_email/backends/__init__.py
templated_email/backends/mailchimp_sts.py
templated_email/backends/postageapp_backend.py
templated_email/backends/vanilla_django.py