Metadata-Version: 1.1
Name: django-templated-email-django-upgrade
Version: 0.5.0
Summary: Fork of a Django oriented templated / transaction email abstraction
Home-page: http://github.com/bharadwaj6/django-templated-email/
Author: Bharadwaj Srigiriraju
Author-email: krishna.bharadwaj6@gmail.com
License: MIT
Platform: any
Classifier: Development Status :: 5 - Production/Stable
Classifier: Intended Audience :: Developers
Classifier: License :: OSI Approved :: MIT License
Classifier: Operating System :: OS Independent
Classifier: Programming Language :: Python
Classifier: Topic :: Software Development :: Libraries :: Python Modules
Classifier: Framework :: Django
